shuup_admin_channel/__init__.py
shuup_admin_channel/apps.py
shuup_admin_channel/browser_config.py
shuup_admin_channel/consumers.py
shuup_admin_channel/handlers.py
shuup_admin_channel/resources.py
shuup_admin_channel/settings.py
shuup_admin_channel/signal_handling.py
shuup_admin_channel/urls.py
shuup_admin_channel/utils.py
shuup_admin_channel/static/shuup-admin-channel.js
shuup_admin_channel_tests/__init__.py
shuup_admin_channel_tests/settings.py
shuup_admin_channel_tests/test_app.py
shuup_admin_channel-1.0.0.dist-info/LICENSE
shuup_admin_channel-1.0.0.dist-info/METADATA
shuup_admin_channel-1.0.0.dist-info/WHEEL
shuup_admin_channel-1.0.0.dist-info/entry_points.txt
shuup_admin_channel-1.0.0.dist-info/top_level.txt
shuup_admin_channel-1.0.0.dist-info/RECORD
