Metadata-Version: 2.1
Name: shuup-admin-channel
Version: 1.0.0
Summary: Adds a generic and extendable channel to Admin module using Shuup Channels.
Home-page: https://github.com/chessbr/shuup-admin-channel
Author: Christian Hess
Author-email: UNKNOWN
License: MIT
Keywords: shuup websocket channels
Platform: UNKNOWN
Requires-Dist: shuup
Requires-Dist: shuup-channels
